tweet_delete/__init__.py
tweet_delete/deleter.py
tweet_delete/entry.py
tweet_delete/main.py
tweet_delete/util.py
tweet_delete-0.3.0.dist-info/entry_points.txt
tweet_delete-0.3.0.dist-info/LICENSE
tweet_delete-0.3.0.dist-info/WHEEL
tweet_delete-0.3.0.dist-info/METADATA
tweet_delete-0.3.0.dist-info/RECORD
