Metadata-Version: 2.1
Name: tweet-delete
Version: 0.3.0
Summary: Self-destructing Tweet tool
Home-page: https://github.com/brndnmtthws/tweet-delete
License: MIT
Author: Brenden Matthews
Author-email: brenden@brndn.io
Requires-Python: >=3.8,<4.0
Classifier: License :: OSI Approved :: MIT License
Classifier: Programming Language :: Python :: 3
Classifier: Programming Language :: Python :: 3.8
Classifier: Programming Language :: Python :: 3.9
Classifier: Programming Language :: Python :: 3.10
Classifier: Programming Language :: Python :: 3.11
Requires-Dist: Pygments (>=2.6.1,<3.0.0)
Requires-Dist: click (>=7.1.2,<9.0.0)
Requires-Dist: colorama (>=0.4.3,<0.5.0)
Requires-Dist: gevent (>=20.6.2,<23.0.0)
Requires-Dist: numpy (>=1.19.1,<2.0.0)
Requires-Dist: python-dateutil (>=2.8.1,<3.0.0)
Requires-Dist: python-twitter (>=3.5,<4.0)
Requires-Dist: pytimeparse (>=1.1.8,<2.0.0)
Requires-Dist: sparklines (>=0.4.2,<0.5.0)
Project-URL: Bug Tracker, https://github.com/brndnmtthws/tweet-delete/issues
Project-URL: Documentation, https://github.com/brndnmtthws/tweet-delete/blob/master/README.md
Project-URL: GitHub, https://github.com/brndnmtthws/tweet-delete
Project-URL: Repository, https://github.com/brndnmtthws/tweet-delete.git
